Metadata-Version: 1.1
Name: mypackage-da-dec21
Version: 0.0.1
Summary: An example package
Home-page: https://github.com/dilip-albert-datascientist/mypackage_da_dec21
Author: Dilip Albert
Author-email: dilip_albert_datascientist@outlook.com
License: MIT
Platform: UNKNOWN
Classifier: Development Status :: 2 - Pre-Alpha
Classifier: License :: OSI Approved :: MIT License
Classifier: Programming Language :: Python
Classifier: Programming Language :: Python :: 2
Classifier: Programming Language :: Python :: 2.7
Classifier: Programming Language :: Python :: 3
Classifier: Programming Language :: Python :: 3.4
Classifier: Programming Language :: Python :: 3.5
Classifier: Programming Language :: Python :: 3.6
Classifier: Programming Language :: Python :: 3.7
